integerbook/__init__.py
integerbook/bar.py
integerbook/chord.py
integerbook/main_converter.py
integerbook/note.py
integerbook/run_single.py
integerbook/sheet.py
integerbook/canvas/__init__.py
integerbook/canvas/canvas_manager.py
integerbook/canvas/patches.py
integerbook/canvas/patches_repeat_expression.py
integerbook/parser/__init__.py
integerbook/parser/bar_repeat_parsers.py
integerbook/parser/bar_vline_parsers.py
integerbook/parser/base_parser.py
integerbook/parser/chordKindAbbreviations.json
integerbook/parser/chord_note_parser.py
integerbook/parser/chord_parser.py
integerbook/parser/glissando_parser.py
integerbook/parser/grace_note_parser.py
integerbook/parser/location_parser.py
integerbook/parser/lyric_parser.py
integerbook/parser/main_parser.py
integerbook/parser/misc_parser.py
integerbook/parser/note_parser.py
integerbook/parser/parse_settings.json
integerbook/parser/parse_settings.py
integerbook/parser/preprocessor.py
integerbook/parser/repeat_expression_parser.py
integerbook/parser/string_articulation_parser.py
integerbook/plotter/__init__.py
integerbook/plotter/barline_plotter.py
integerbook/plotter/base_plotter.py
integerbook/plotter/chord_plotter.py
integerbook/plotter/glissando_plotter.py
integerbook/plotter/grace_note_plotter.py
integerbook/plotter/key_origin_plotter.py
integerbook/plotter/lyric_plotter.py
integerbook/plotter/main_plotter.py
integerbook/plotter/measure_divider_plotter.py
integerbook/plotter/metadata_plotter.py
integerbook/plotter/note_plotter.py
integerbook/plotter/plot_settings.json
integerbook/plotter/plot_settings.py
integerbook/plotter/repeat_bracket_plotter.py
integerbook/plotter/repeat_expression_plotter.py
integerbook/plotter/string_articulation_plotter.py
integerbook/plotter/x_location_finder.py
integerbook/plotter/y_location_finder.py
integerbook/tests/__init__.py
integerbook/tests/test.py
integerbook-0.2.5.dist-info/licenses/LICENSE
integerbook-0.2.5.dist-info/METADATA
integerbook-0.2.5.dist-info/WHEEL
integerbook-0.2.5.dist-info/top_level.txt
integerbook-0.2.5.dist-info/RECORD
