Metadata-Version: 2.4
Name: integerbook
Version: 0.2.5
Summary: sheet music converter
Author-email: Jesse van Oostrum <integerbook@gmail.com>
License:                     GNU GENERAL PUBLIC LICENSE
Project-URL: Homepage, https://github.com/jessevoostrum/music-visualisation
Keywords: music
Classifier: License :: OSI Approved :: MIT License
Classifier: Programming Language :: Python
Classifier: Programming Language :: Python :: 3
Requires-Python: >=3.9
License-File: LICENSE
Requires-Dist: music21>=8
Dynamic: license-file
